[{"name": "Shop on eBay", "price": 2000, "status": "Brand New", "shipping": null, "free_returns": false, "items_sold": null}, {"name": "Algorithms to Live By: The Computer Science of Human Decisions - GOOD", "price": 793, "status": "Pre-Owned", "shipping": 0, "free_returns": true, "items_sold": 43}, {"name": "Python Programming: An Introduction to Computer Science - Paperback - GOOD", "price": 525, "status": "Pre-Owned", "shipping": 0, "free_returns": true, "items_sold": null}, {"name": "Barron's AP Computer Science A, 8th Edition: with Bonus Online Tests - GOOD", "price": 404, "status": "Pre-Owned", "shipping": 0, "free_returns": true, "items_sold": null}, {"name": "5 Steps to a 5 AP Computer Science Principles - Paperback By Sway, Julie - GOOD", "price": 439, "status": "Pre-Owned", "shipping": 0, "free_returns": true, "items_sold": null}, {"name": "Computer Science Programming Basics in Ruby: Exploring Concepts and...", "price": 427, "status": "Pre-Owned", "shipping": 0, "free_returns": true, "items_sold": null}, {"name": "Practical Programming: An Introduction to Computer Science Using Python", "price": 409, "status": "Pre-Owned", "shipping": 0, "free_returns": true, "items_sold": null}, {"name": "Numerical Python  Scientific Computing and Data Science Applicati", "price": 1199, "status": "Brand New", "shipping": 0, "free_returns": false, "items_sold": 31}, {"name": "Elements of Programming Interviews in Python: The Insiders' Guide by Lee: New", "price": 1695, "status": "New (Other)", "shipping": 0, "free_returns": true, "items_sold": 15}, {"name": "Computer Science I Essentials (Essentials Study Guides) by Research and Educati", "price": 549, "status": "Pre-Owned", "shipping": 0, "free_returns": false, "items_sold": null}, {"name": "Be Prepared for the AP Computer Science Exam in Java", "price": 750, "status": "Pre-Owned", "shipping": 0, "free_returns": true, "items_sold": null}, {"name": "Elements of Programming Interviews in Python: The Insiders' Guide by Lee: New", "price": 1800, "status": "Brand New", "shipping": 0, "free_returns": false, "items_sold": null}, {"name": "The Art Of Computer Programming Volume 1 By Donald E. Knuth Book 2005", "price": 3499, "status": "Pre-Owned", "shipping": 416, "free_returns": false, "items_sold": null}, {"name": "Mathematical Structures for Computer Science : A Modern Treatment", "price": 597, "status": "Pre-Owned", "shipping": 0, "free_returns": false, "items_sold": null}, {"name": "AP Computer Science Principles Premium with 6 Practice Tests: With 6... PAPER...", "price": 2395, "status": "Brand New", "shipping": 599, "free_returns": true, "items_sold": null}, {"name": "Studies in Computational Science: Parallel Programming Paradigms", "price": 5619, "status": "Pre-Owned", "shipping": 0, "free_returns": true, "items_sold": null}, {"name": "The Algorithm Design Manual (Texts in Computer Science) 3rd ed. 2020 Edition ...", "price": 12295, "status": "New (Other)", "shipping": 589, "free_returns": true, "items_sold": null}, {"name": "Lecture Notes in Computer Science Ser.: Teaching Fundamentals Concepts of...", "price": 4999, "status": "Brand New", "shipping": 1260, "free_returns": false, "items_sold": null}, {"name": "Fundamental Proof Methods in Computer Science: A Computer-Based Approach (The MI", "price": 716, "status": "New (Other)", "shipping": 0, "free_returns": true, "items_sold": null}, {"name": "Lecture Notes in Computer Science Ser.: Software Product Lines : Second...", "price": 14999, "status": "Brand New", "shipping": 1260, "free_returns": false, "items_sold": null}, {"name": "Lecture Notes in Computer Science Ser.: Pattern Recognition and Computer Vision", "price": 3199, "status": "Pre-Owned", "shipping": 0, "free_returns": false, "items_sold": null}, {"name": "Lecture Notes in Computer Science Ser.: Implementation and Application of...", "price": 13999, "status": "Pre-Owned", "shipping": 5770, "free_returns": false, "items_sold": null}, {"name": "Microcomputing by Timothy J. O'Leary Brian K Williams Linda I O'Leary textbook", "price": 300, "status": "Pre-Owned", "shipping": 617, "free_returns": false, "items_sold": null}, {"name": "Lecture Notes in Computer Science Ser.: Computational Science-ICCS 2002 Part III", "price": 12999, "status": "Brand New", "shipping": 2505, "free_returns": false, "items_sold": null}, {"name": "Reactive Applications with Akka.NET by Anthony Brown", "price": 1500, "status": "New (Other)", "shipping": 416, "free_returns": false, "items_sold": null}, {"name": "Programming Language Pragmatics, Paperback by Scott, Michael L., used very good", "price": 6500, "status": "Pre-Owned", "shipping": 416, "free_returns": false, "items_sold": null}, {"name": "Computer Science in K-12: An A-To-Z Handbook on Teac... 9781734662702 by Unknown", "price": 2382, "status": "New (Other)", "shipping": 399, "free_returns": false, "items_sold": null}, {"name": "Encyclopedia of Computer Science and Technology Hardcover Harry H", "price": 686, "status": "Pre-Owned", "shipping": 0, "free_returns": false, "items_sold": null}, {"name": "Introduction To Algorithms Paperback Thomas H. Cormen", "price": 890, "status": "Pre-Owned", "shipping": 483, "free_returns": false, "items_sold": null}, {"name": "COORDINATION MODELS AND LANGUAGES LNCS 5052 10TH International Conference", "price": 1531, "status": "Pre-Owned", "shipping": 416, "free_returns": true, "items_sold": null}, {"name": "Handbook of Theoretical Computer Science - 2 Vol Set by van Leeuwen, Jan", "price": 24041, "status": "Pre-Owned", "shipping": 0, "free_returns": true, "items_sold": null}, {"name": "1997 Vintage Book International Symposium on Low Power Electronics And Design ", "price": 17500, "status": "New (Other)", "shipping": 1327, "free_returns": true, "items_sold": null}, {"name": "Continuing BASIC by P.E. Gosling (Paperback, 1980) - COLLECTORS ITEM", "price": 1768, "status": "Pre-Owned", "shipping": 4237, "free_returns": false, "items_sold": null}, {"name": "Barron's AP Computer Science A Flash Cards by Roselyn Teukolsky: Used", "price": 1353, "status": "Pre-Owned", "shipping": 449, "free_returns": false, "items_sold": null}, {"name": "Word 97 for Busy People by Christian Crumlish", "price": 1999, "status": "Pre-Owned", "shipping": 416, "free_returns": false, "items_sold": null}, {"name": "TRS-80 POCKET COMPUTER PROGRAMS MANUAL By Jim Cole Good Used Condition", "price": 1999, "status": "Pre-Owned", "shipping": 349, "free_returns": false, "items_sold": null}, {"name": "Practical Programming: An Introduction to Computer Science Using Python 3 - GOOD", "price": 645, "status": "Pre-Owned", "shipping": 0, "free_returns": true, "items_sold": null}, {"name": "Signal Processing First McClellan Schaefer Yoder 2003 Paperback", "price": 1789, "status": "Pre-Owned", "shipping": 541, "free_returns": true, "items_sold": null}, {"name": "200+ WAYS TO PROTECT YOUR PRIVACY", "price": 354, "status": "Brand New", "shipping": 352, "free_returns": false, "items_sold": null}, {"name": "Cracking the AP Computer Science A Exam, 2020 Edition: Practice Tests & P - GOOD", "price": 457, "status": "Pre-Owned", "shipping": 0, "free_returns": true, "items_sold": null}, {"name": "Lecture Notes in Computer Science Ser.: Biomedical Image Registration : 8th...", "price": 700, "status": "Pre-Owned", "shipping": 349, "free_returns": false, "items_sold": null}, {"name": "Official CompTIA CySA+ Student Guide : Exam CS0-002 (2020, Pbk) James Pengelly", "price": 5750, "status": "Pre-Owned", "shipping": 0, "free_returns": false, "items_sold": null}, {"name": "Computer Science Unle... 9780997316056 by Ferreira Filho, Wladston, Pictet, Moto", "price": 2594, "status": "New (Other)", "shipping": 399, "free_returns": false, "items_sold": null}, {"name": "Hodder Education Edexcel GCSE Computer Science My Revision Notes Steve Cushing", "price": 1060, "status": "Brand New", "shipping": 2184, "free_returns": false, "items_sold": null}, {"name": "Programmable Logic Controllers by Frank D. Petruzella (2004, Hardcover, Textbook", "price": 189, "status": "Pre-Owned", "shipping": 508, "free_returns": false, "items_sold": null}, {"name": "Communicating Sequential Processes Hardcover C.A.R. Hoare", "price": 2299, "status": "Pre-Owned", "shipping": 0, "free_returns": false, "items_sold": null}, {"name": "Discovering Computer Science by Jessen Havill", "price": 2095, "status": "Pre-Owned", "shipping": 399, "free_returns": false, "items_sold": null}, {"name": "Programming in Ada: an introduction by means of graduated examples", "price": 117, "status": "Pre-Owned", "shipping": 3070, "free_returns": false, "items_sold": null}, {"name": "Innovate with Sense HAT for Raspberry Pi, By Dogan Ibrahim ", "price": 2274, "status": "Brand New", "shipping": 199, "free_returns": false, "items_sold": null}, {"name": "Windows Vista Plain & Simple by Gerald Joyce, Marianne Moon (Paperback, 2006)", "price": 118, "status": "Pre-Owned", "shipping": 3147, "free_returns": false, "items_sold": null}, {"name": "Flat-Panel Displays and CRTs (Van Nostrand Reinhold Electrical/Computer Science", "price": 5028, "status": "Pre-Owned", "shipping": 399, "free_returns": false, "items_sold": null}, {"name": "The Innovators: How a Group of Hackers, Geniuses, and Geeks Created  - VERY GOOD", "price": 358, "status": "Pre-Owned", "shipping": 0, "free_returns": true, "items_sold": null}, {"name": "Windows 7 Plain & Simple by Marianne Moon, Gerald Joyce (Paperback, 2009)", "price": 118, "status": "New (Other)", "shipping": 3147, "free_returns": false, "items_sold": null}, {"name": "Microsoft Windows Networking Essentials -Paperback - Exam 98-366", "price": 117, "status": "Pre-Owned", "shipping": 3141, "free_returns": false, "items_sold": null}, {"name": "Applied Cryptography: Protocols, Algorithms and Source Code in C (Computer Scien", "price": 785, "status": "Pre-Owned", "shipping": 217, "free_returns": false, "items_sold": null}, {"name": "Help Your Kids with Computer Science by DK: Used", "price": 450, "status": "Pre-Owned", "shipping": 449, "free_returns": false, "items_sold": null}, {"name": "New GCSE Computer Science OCR Complete Revision & Practice - Grade 9-1 (with Onl", "price": 317, "status": "Pre-Owned", "shipping": 217, "free_returns": false, "items_sold": null}, {"name": "Analysis of Algorithms by Jeffrey McConnell (2007, Hardcover, Second edition)", "price": 5004, "status": "New (Other)", "shipping": 199, "free_returns": false, "items_sold": null}, {"name": "Computer Science: An Overview (11th Edition)", "price": 3599, "status": "Pre-Owned", "shipping": 499, "free_returns": false, "items_sold": null}, {"name": "C++ For Dummies by Davis, Stephen R., 4th edition *no CD ROM with it*", "price": 117, "status": "Pre-Owned", "shipping": 3153, "free_returns": false, "items_sold": null}, {"name": "How to solve it with Prologue. Laboratorio Nacional de Engenharia Civil, 1982", "price": 117, "status": "Pre-Owned", "shipping": 3070, "free_returns": false, "items_sold": null}, {"name": "Kids Biz Guide To Starting An Online Business", "price": 799, "status": "New (Other)", "shipping": 1060, "free_returns": true, "items_sold": null}, {"name": "A Theory of Objects (Monographs in Computer Science), Cardelli, Luca,Abadi, Mart", "price": 6633, "status": "Pre-Owned", "shipping": 0, "free_returns": false, "items_sold": null}, {"name": "Computer Science Today: Recent Trends and Developments: ... Paperback / softback", "price": 4560, "status": "Pre-Owned", "shipping": 0, "free_returns": false, "items_sold": null}, {"name": "Great Jobs for Computer Science Majors by Goldberg, Jan", "price": 662, "status": "Pre-Owned", "shipping": 0, "free_returns": true, "items_sold": null}, {"name": "Automate the Boring Stuff with Python, 2nd Edition: Practical Programming for To", "price": 2057, "status": "Pre-Owned", "shipping": 0, "free_returns": true, "items_sold": null}, {"name": "Computer Science Distilled: Learn The Art Of Solving Computational Problems", "price": 2130, "status": "Brand New", "shipping": 0, "free_returns": false, "items_sold": null}, {"name": "Computer Coding for Kids By Carol Vorderman", "price": 348, "status": "New (Other)", "shipping": 2363, "free_returns": false, "items_sold": null}, {"name": "2000 Reader's Digest How To Do Just About Anything on A Computer with CD Disc", "price": 889, "status": "Pre-Owned", "shipping": 399, "free_returns": true, "items_sold": null}, {"name": "The CRPG Book: A Guide to Computer Role Playing Games dungeon map pad", "price": 2233, "status": "Pre-Owned", "shipping": 3714, "free_returns": false, "items_sold": null}, {"name": "Turing's Cathedral: The Origins of the Digital Universe - Hardcover - GOOD", "price": 409, "status": "Pre-Owned", "shipping": 0, "free_returns": true, "items_sold": null}, {"name": "37th Symp Foundation Computer Science by IEEE Computer Society; IEEE", "price": 1932, "status": "Pre-Owned", "shipping": 0, "free_returns": true, "items_sold": null}, {"name": "Computer Science: a Very Short Introduction Paperback Subrata Das", "price": 673, "status": "Pre-Owned", "shipping": 0, "free_returns": false, "items_sold": null}, {"name": "Computer Programming books 6 Full Bookshelves    Best Offer", "price": 100000, "status": "Pre-Owned", "shipping": null, "free_returns": false, "items_sold": null}, {"name": "S-Parameters for Signal Integrity by Peter J. Pupalaikis Hardcover 9781108489966", "price": 6009, "status": "New (Other)", "shipping": 2592, "free_returns": false, "items_sold": null}, {"name": "The Theory of Computation by Moret, B. M. E.; Moret, Bernard M.", "price": 2337, "status": "Pre-Owned", "shipping": 0, "free_returns": true, "items_sold": null}, {"name": "Shop on eBay", "price": 2000, "status": "Brand New", "shipping": null, "free_returns": false, "items_sold": null}, {"name": "The Theory of Computation by Moret, B. M. E.; Moret, Bernard M.", "price": 2337, "status": "Pre-Owned", "shipping": 0, "free_returns": true, "items_sold": null}, {"name": " LIKE NEW Lecture Notes in Computer Science: Advances in Cryptology -EUROCRYPT ", "price": 3999, "status": "New (Other)", "shipping": 0, "free_returns": false, "items_sold": null}, {"name": "Digital Logic & Computer Operations Baron Piccirilli 1967 Vintage Computing Book", "price": 4300, "status": "New (Other)", "shipping": 0, "free_returns": true, "items_sold": null}, {"name": "Python Crash Course, 3rd Edition 3rd Edition Paperback by Eric Matthes", "price": 3495, "status": "New (Other)", "shipping": 596, "free_returns": true, "items_sold": null}, {"name": "37th Symp Foundation Computer Science by IEEE Computer Society; IEEE", "price": 1932, "status": "Pre-Owned", "shipping": 0, "free_returns": true, "items_sold": null}, {"name": "Computer Science: a Very Short Introduction Paperback Subrata Das", "price": 673, "status": "Pre-Owned", "shipping": 0, "free_returns": false, "items_sold": null}, {"name": "Computer Programming books 6 Full Bookshelves    Best Offer", "price": 100000, "status": "Pre-Owned", "shipping": null, "free_returns": false, "items_sold": null}, {"name": "Computer Science Principles: The Foundational Concepts of Compute", "price": 533, "status": "New (Other)", "shipping": 0, "free_returns": true, "items_sold": null}, {"name": "Database Systems (Macmillan Computer Science),Paul Beynon-Davi ,", "price": 546, "status": "Pre-Owned", "shipping": 1060, "free_returns": false, "items_sold": null}, {"name": "Predictive Modeling with SAS Enterprise Miner: Practical Solutions for Business", "price": 189, "status": "New (Other)", "shipping": 508, "free_returns": false, "items_sold": null}, {"name": "The Genealogist's Internet by Peter Christian (Paperback, 2005)", "price": 117, "status": "Pre-Owned", "shipping": 3077, "free_returns": false, "items_sold": null}, {"name": "Mathematical Modelling Techniques by Aris, Rutherford", "price": 986, "status": "Pre-Owned", "shipping": 0, "free_returns": true, "items_sold": null}, {"name": "Borland C++ 2.0 Programming Windows 3.0 Ben Ezzell 1991 Computer tech NO DISK!!!", "price": 2000, "status": "Pre-Owned", "shipping": 650, "free_returns": false, "items_sold": null}, {"name": "Elements of Computer Security (Undergraduate Topics in Computer Science) - GOOD", "price": 948, "status": "Pre-Owned", "shipping": 0, "free_returns": true, "items_sold": null}, {"name": "Advances in Neuro-Information Processing: 15th International Conference, ICON...", "price": 28166, "status": "Brand New", "shipping": 0, "free_returns": false, "items_sold": null}, {"name": "Transactions on Computational Science XXVI: Special Issue on Cyberworlds and ...", "price": 9257, "status": "Brand New", "shipping": 0, "free_returns": false, "items_sold": null}, {"name": "Computer Science Companion Spiral William T. VERTS", "price": 702, "status": "Pre-Owned", "shipping": 0, "free_returns": false, "items_sold": null}, {"name": "Logic in Computer Science : Modelling and Reasoning about Systems by Mark...", "price": 4595, "status": "Pre-Owned", "shipping": 0, "free_returns": false, "items_sold": null}, {"name": "Comparative Programming Languages (International Computer Science Series) - GOOD", "price": 776, "status": "Pre-Owned", "shipping": 0, "free_returns": true, "items_sold": null}, {"name": "Automata Networks in Computer Science Hardcover Francoise Fogelma", "price": 489, "status": "Pre-Owned", "shipping": 0, "free_returns": false, "items_sold": null}, {"name": "Lecture Notes in Computational Science and Engineering Ser.: Numerical...", "price": 4999, "status": "Pre-Owned", "shipping": 0, "free_returns": true, "items_sold": null}, {"name": "Computing Tomorrow : The Future of Research in Computer Science H", "price": 495, "status": "Pre-Owned", "shipping": 0, "free_returns": false, "items_sold": null}, {"name": "Python Crash Course, 2nd Edition : A Hands-On, Project-Based Introduction to...", "price": 3000, "status": "New (Other)", "shipping": 600, "free_returns": false, "items_sold": null}, {"name": "Matlab : A Practical Introduction to Programming and Problem Solving by...", "price": 1600, "status": "Pre-Owned", "shipping": 0, "free_returns": false, "items_sold": null}, {"name": "(Good)-A/AS Level Computer Science for WJEC/Eduqas Student Book (A Level Comp 2 ", "price": 4012, "status": "Pre-Owned", "shipping": 6365, "free_returns": false, "items_sold": null}, {"name": "Linear Programming and Economic Analysis", "price": 1827, "status": "Pre-Owned", "shipping": 0, "free_returns": true, "items_sold": null}, {"name": "Computer Science Problem Solver Research &amp; Education Associat", "price": 699, "status": "Pre-Owned", "shipping": 0, "free_returns": true, "items_sold": null}, {"name": "Grand Thieves & Tomb Raiders How British Video Games 04-6-1", "price": 295, "status": "Brand New", "shipping": 3146, "free_returns": false, "items_sold": null}, {"name": "Lecture Notes in Computer Science Ser.: Computational Modeling of Objects Presen", "price": 8096, "status": "Pre-Owned", "shipping": 2320, "free_returns": true, "items_sold": null}, {"name": "Android Programming NEW English Phillips Bill Pearson Education US Hardback", "price": 42375, "status": "Brand New", "shipping": 2002, "free_returns": false, "items_sold": null}, {"name": "Future Generation Grids  CoreGrid ", "price": 22881, "status": "Brand New", "shipping": 0, "free_returns": false, "items_sold": null}, {"name": "Intelligent User Interfaces 2010 - Unknown Binding - GOOD", "price": 29892, "status": "Pre-Owned", "shipping": 0, "free_returns": true, "items_sold": null}, {"name": "Great Ideas in Computer Science : A Gentle Introduction Alan W. B", "price": 582, "status": "Pre-Owned", "shipping": 0, "free_returns": false, "items_sold": null}, {"name": "Feynman Lectures On Computation [Frontiers in Physics]", "price": 2597, "status": "Pre-Owned", "shipping": 0, "free_returns": false, "items_sold": null}, {"name": "Undergraduate Texts in Computer Science Ser.: Automata and Computability by...", "price": 6772, "status": "Pre-Owned", "shipping": 0, "free_returns": false, "items_sold": null}, {"name": "Introduction to Algorithms, Second Edition - Hardcover - GOOD", "price": 1591, "status": "Pre-Owned", "shipping": 0, "free_returns": true, "items_sold": 7}, {"name": "Help Your Kids with Computer Science by DK", "price": 631, "status": "Pre-Owned", "shipping": 0, "free_returns": true, "items_sold": null}, {"name": "(ISC)2 CISSP Official Study Guide / Practice Test Bundle (Brand New!)", "price": 5499, "status": "Brand New", "shipping": 617, "free_returns": false, "items_sold": null}, {"name": "Advanced Data Mining and Applications", "price": 24467, "status": "Brand New", "shipping": 0, "free_returns": false, "items_sold": null}, {"name": "Algorithms and Computation", "price": 12824, "status": "Brand New", "shipping": 0, "free_returns": false, "items_sold": null}, {"name": "Help Your Kids with Computer Science Paperback DK", "price": 557, "status": "Pre-Owned", "shipping": 0, "free_returns": false, "items_sold": null}, {"name": "Computer Science : A Structured Programming Approach Using C Pape", "price": 597, "status": "Pre-Owned", "shipping": 0, "free_returns": false, "items_sold": null}, {"name": "Designing And Developing Windows Based Applications Using .NET 2007 PREOWNED", "price": 4999, "status": "New (Other)", "shipping": 0, "free_returns": true, "items_sold": null}, {"name": "Understanding Computer Science by Walker, Roger S.", "price": 1312, "status": "Pre-Owned", "shipping": 0, "free_returns": true, "items_sold": null}, {"name": "Invitation to Computer Science by Schneider, G. Michael; Gersting, Judith", "price": 797, "status": "Pre-Owned", "shipping": 0, "free_returns": true, "items_sold": null}, {"name": "Facts on File Dictionary of Computer Science Hardcover Valerie Il", "price": 623, "status": "Pre-Owned", "shipping": 0, "free_returns": false, "items_sold": null}, {"name": "Computer Simulation in Management Science, 4th Edition By Michae", "price": 1051, "status": "Pre-Owned", "shipping": 0, "free_returns": false, "items_sold": null}, {"name": "Computer Science Distilled: Learn the Art of Solving ... by Ferreira Filho, Wlad", "price": 2059, "status": "Pre-Owned", "shipping": 0, "free_returns": false, "items_sold": null}, {"name": "Ivor Horton's Beginning Visual C++ 2012 by Ivor Horton (Paperback, 2012)", "price": 471, "status": "Pre-Owned", "shipping": 3155, "free_returns": false, "items_sold": null}, {"name": "Great Principles of Computing (The MIT Press)", "price": 1280, "status": "New (Other)", "shipping": 0, "free_returns": true, "items_sold": null}, {"name": "Facts on File Dictionary of Computer Science Hardcover Valerie Il", "price": 623, "status": "Pre-Owned", "shipping": 0, "free_returns": true, "items_sold": null}, {"name": "Computing Tomorrow : The Future of Research in Computer Science I", "price": 495, "status": "Pre-Owned", "shipping": 0, "free_returns": false, "items_sold": null}, {"name": "Naive Set Theory by Paul R Halmos: New", "price": 745, "status": "Brand New", "shipping": 449, "free_returns": false, "items_sold": null}, {"name": "Introduction to Subsurface Imaging, , Very Good condition, Book", "price": 2652, "status": "Pre-Owned", "shipping": 1177, "free_returns": false, "items_sold": null}, {"name": "Computer Science Companion - Spiral-bound By VERTS  WILLIAM T - GOOD", "price": 880, "status": "Pre-Owned", "shipping": 0, "free_returns": true, "items_sold": null}, {"name": "Elements of Programming Interviews in Python: The Insiders' Guide by Lee: New", "price": 2100, "status": "Brand New", "shipping": 0, "free_returns": false, "items_sold": null}, {"name": "AP Computer Science Perfect Kathleen A. Larson", "price": 501, "status": "Pre-Owned", "shipping": 0, "free_returns": false, "items_sold": null}, {"name": "Revise OCR GCSE (9-1) Computer Science Revision Workbook:for the 9-1  exams (REV", "price": 445, "status": "Pre-Owned", "shipping": 217, "free_returns": false, "items_sold": null}, {"name": "Geometric Fundamentals of Robotics [Monographs in Computer Science]", "price": 4372, "status": "Pre-Owned", "shipping": 0, "free_returns": false, "items_sold": null}, {"name": "Word 2000 for Windows For Dummies by Dan Gookin (Paperback, 1999)", "price": 117, "status": "Pre-Owned", "shipping": 3147, "free_returns": false, "items_sold": null}, {"name": "(ISC)2 CISSP Certified Information Systems Security Study Guide & Practice Tests", "price": 1599, "status": "New (Other)", "shipping": 0, "free_returns": false, "items_sold": null}, {"name": "NEW 3 Days US Artificial Intelligence A Modern Approach 3E Russell 3rd Paperback", "price": 7990, "status": "Brand New", "shipping": 0, "free_returns": false, "items_sold": null}, {"name": "Introduction to Computer Science: Programming 2nd Edition Hardback Nance/Naps", "price": 2000, "status": "Pre-Owned", "shipping": 684, "free_returns": false, "items_sold": null}, {"name": "5 Steps to a 5: AP Computer Science A 2019 Paperback Dean R. John", "price": 501, "status": "Pre-Owned", "shipping": 0, "free_returns": false, "items_sold": null}, {"name": "Dynamics in Document Design : Creating Text for Readers by Karen A. Schriver...", "price": 450, "status": "Pre-Owned", "shipping": 416, "free_returns": false, "items_sold": null}, {"name": "Managerial Issues of Enterprise Resource... by Olson, David Paperback / softback", "price": 846, "status": "Pre-Owned", "shipping": 0, "free_returns": false, "items_sold": null}, {"name": "Geometrical Methods in Robotics [Monographs in Computer Science]", "price": 1952, "status": "Pre-Owned", "shipping": 0, "free_returns": false, "items_sold": null}, {"name": "Logic in Computer Science: Modelling and Reasoning about Systems by Huth, Micha", "price": 2594, "status": "Pre-Owned", "shipping": 0, "free_returns": false, "items_sold": null}, {"name": "Dover Books on Computer Science Ser.: Discrete Optimization Algorithms : With Pa", "price": 600, "status": "Pre-Owned", "shipping": 416, "free_returns": true, "items_sold": null}, {"name": "Conditionals: From Philosophy to Computer Science (Studies in Logic and Computat", "price": 3653, "status": "Pre-Owned", "shipping": 0, "free_returns": true, "items_sold": null}, {"name": "Software Design (International Computer Science) By David Budgen", "price": 1157, "status": "Pre-Owned", "shipping": 0, "free_returns": false, "items_sold": null}, {"name": "Database System Concepts (Int'l Ed) by Abraham Silberschatz, Henry Korth, S....", "price": 589, "status": "Pre-Owned", "shipping": 1291, "free_returns": false, "items_sold": null}, {"name": "XML: Visual QuickStart Guide by Kevin Howard Goldberg (Paperback)", "price": 589, "status": "New (Other)", "shipping": 3222, "free_returns": false, "items_sold": null}, {"name": "Software Quality - ECSQ 2002", "price": 12711, "status": "Brand New", "shipping": 0, "free_returns": false, "items_sold": null}, {"name": "Solve It!: Computer-Aided Mathematics for Science and Engineerin", "price": 2585, "status": "Pre-Owned", "shipping": 0, "free_returns": false, "items_sold": null}, {"name": "Shop on eBay", "price": 2000, "status": "Brand New", "shipping": null, "free_returns": false, "items_sold": null}, {"name": "The Z Notation: A Reference Manual by Spivey, J.", "price": 705, "status": "Pre-Owned", "shipping": 0, "free_returns": true, "items_sold": null}, {"name": "Coding in the Classroom: Why You Should Care About Teaching Computer Science", "price": 782, "status": "New (Other)", "shipping": 0, "free_returns": true, "items_sold": null}, {"name": "Rough Sets and Knowledge Technology: 4th International Conference, RSKT 2009,...", "price": 22001, "status": "Brand New", "shipping": 0, "free_returns": false, "items_sold": null}, {"name": "Advances in Intelligent Data Analysis IX  9th International Sympo", "price": 11332, "status": "Pre-Owned", "shipping": 0, "free_returns": false, "items_sold": null}, {"name": "ITIL Service Strategy By Axelos Gc 2016", "price": 1177, "status": "Pre-Owned", "shipping": 3366, "free_returns": false, "items_sold": null}, {"name": "The Pragmatic Programmer by David Thomas, Andrew Hunt, Paperback", "price": 2356, "status": "Pre-Owned", "shipping": 2804, "free_returns": false, "items_sold": null}, {"name": "Learning PHP Design Patterns by William Sanders (Paperback)", "price": 1473, "status": "Brand New", "shipping": 3242, "free_returns": false, "items_sold": null}, {"name": "Help Your Kids with Computer Science - Paperback By DK - GOOD", "price": 517, "status": "Pre-Owned", "shipping": 0, "free_returns": true, "items_sold": null}, {"name": "Security Engineering: A Guide to Building Depen... by Anderson, Ross J. Hardback", "price": 2356, "status": "Pre-Owned", "shipping": 2804, "free_returns": false, "items_sold": null}, {"name": "PHP Web Services: APIs for the Modern Web by Lorna Mitchell (Paperback)", "price": 684, "status": "Brand New", "shipping": 3225, "free_returns": false, "items_sold": null}, {"name": "Information Architecture for the World Wide Web (Paperback)", "price": 1177, "status": "Brand New", "shipping": 3236, "free_returns": false, "items_sold": null}, {"name": "Parallel Programmming (International Computer Science Se... by Perrott Paperback", "price": 587, "status": "Pre-Owned", "shipping": 0, "free_returns": false, "items_sold": null}, {"name": "Secrets of the JavaScript Ninja by John Resig (Paperback)", "price": 1709, "status": "Brand New", "shipping": 3248, "free_returns": false, "items_sold": null}, {"name": "Transactions on Pattern Languages of Programming I", "price": 13630, "status": "Brand New", "shipping": 0, "free_returns": false, "items_sold": null}, {"name": "Coordination Models and Languages  6th International Conference  ", "price": 12711, "status": "Brand New", "shipping": 0, "free_returns": false, "items_sold": null}, {"name": "Information and Communications Security  12th International Confe", "price": 12711, "status": "Brand New", "shipping": 0, "free_returns": false, "items_sold": null}, {"name": "PHP, MySQL, JavaScript & HTML5 All-in-One For Dummies by Steve Suehring,...", "price": 117, "status": "New (Other)", "shipping": 3276, "free_returns": false, "items_sold": null}, {"name": "The Engaged Customer by Hans Peter Brondmo 9780749922375", "price": 3201, "status": "New (Other)", "shipping": 2823, "free_returns": false, "items_sold": null}, {"name": "Introduction to Computer Science: Programming, Problem Solving, and Data Structu", "price": 1099, "status": "Pre-Owned", "shipping": 0, "free_returns": false, "items_sold": null}, {"name": "Operating System Concepts with Java by Abraham Silberschatz, Peter B. Galvin,...", "price": 354, "status": "New (Other)", "shipping": 1291, "free_returns": false, "items_sold": null}, {"name": "Introduction to Computing: Explorations in Language, Logic, and Machines, Evans,", "price": 1825, "status": "Pre-Owned", "shipping": 0, "free_returns": false, "items_sold": null}, {"name": "Prolog: Programming For Artificial Intelligence (Inte... by Bratko, I. Paperback", "price": 488, "status": "Pre-Owned", "shipping": 0, "free_returns": false, "items_sold": null}, {"name": "Samsung Galaxy S8 For Dummies (For Dummies (Computer/Tech)), Hughes, Bill, Good ", "price": 502, "status": "Pre-Owned", "shipping": 1282, "free_returns": false, "items_sold": null}, {"name": "Texts in Computer Science Ser: Formal Languages & Compilation by S. Reghizzi HC", "price": 1100, "status": "Pre-Owned", "shipping": 400, "free_returns": false, "items_sold": null}, {"name": "The Design and Implementation of the 4.3bsd UNIX Operating System", "price": 629, "status": "Pre-Owned", "shipping": 0, "free_returns": true, "items_sold": null}, {"name": "Problem Solving with Algorithms and Data Structures Using Python, Very Good Cond", "price": 3512, "status": "Pre-Owned", "shipping": 1699, "free_returns": false, "items_sold": null}, {"name": "Computer Science Reconsidered : The Invocation Model of Process E", "price": 2430, "status": "Pre-Owned", "shipping": 0, "free_returns": false, "items_sold": null}, {"name": "Help Your Kids with Computer Science, DK, 9781465473608", "price": 899, "status": "New (Other)", "shipping": 0, "free_returns": false, "items_sold": null}, {"name": "EUNICE 2005  Networks and Applications Towards a Ubiquitously Con", "price": 18418, "status": "Brand New", "shipping": 0, "free_returns": false, "items_sold": null}, {"name": "Coordination Models and Languages  7th International Conference  ", "price": 12655, "status": "Brand New", "shipping": 0, "free_returns": false, "items_sold": null}, {"name": "Controlled Natural Language  Workshop on Controlled Natural Langu", "price": 12655, "status": "Brand New", "shipping": 0, "free_returns": false, "items_sold": null}, {"name": "Developments And Applications Of Block Toeplitz Iterative Solvers (combinator...", "price": 18773, "status": "Brand New", "shipping": 0, "free_returns": false, "items_sold": null}, {"name": "Alexa For Dummies, Very Good Condition, McFedries, Paul, ISBN 1119565863", "price": 1164, "status": "Pre-Owned", "shipping": 962, "free_returns": false, "items_sold": null}, {"name": "Python Tricks: A Buffet of Awesome Python Features, Bader, Dan, Good Condition, ", "price": 1104, "status": "Pre-Owned", "shipping": 1070, "free_returns": false, "items_sold": null}, {"name": "Discovering Computers 2016 Shelly Cashman, Frydenberg, Mark, Campbell, Jennif\u00a0", "price": 1500, "status": "New (Other)", "shipping": 500, "free_returns": false, "items_sold": null}, {"name": "Intelligent Computer Mathematics: 9th International Conference, ", "price": 3523, "status": "Pre-Owned", "shipping": 1060, "free_returns": false, "items_sold": null}, {"name": "Lecture Notes in Computer Science Ser.: Transactions on Aspect-Oriented...", "price": 3052, "status": "New (Other)", "shipping": 0, "free_returns": false, "items_sold": null}, {"name": "AQA GCSE (9-1) Computer Science By S Robson, P M Heathcote", "price": 1137, "status": "Pre-Owned", "shipping": 0, "free_returns": false, "items_sold": null}, {"name": "Knowledge Acquisition  Approaches  Algorithms and Applications  P", "price": 12372, "status": "Brand New", "shipping": 0, "free_returns": false, "items_sold": null}, {"name": "Advances in Geometric Modeling and Processing  6th International ", "price": 12711, "status": "Brand New", "shipping": 0, "free_returns": false, "items_sold": null}, {"name": "Get Set for Computer Science (Get Set for Univ... by Edwards, Alistair Paperback", "price": 664, "status": "Pre-Owned", "shipping": 0, "free_returns": false, "items_sold": null}, {"name": "Data Compression : Methods and Theory Hardcover James A. Storer", "price": 543, "status": "Pre-Owned", "shipping": 0, "free_returns": false, "items_sold": null}, {"name": "Introduction to computer science by Murrill, Paul W", "price": 2324, "status": "Pre-Owned", "shipping": 0, "free_returns": true, "items_sold": null}, {"name": "Press Reset: Ruin and Recovery in the Video Game Industry, Very Good Condition, ", "price": 923, "status": "Pre-Owned", "shipping": 641, "free_returns": false, "items_sold": null}, {"name": "Epidemics: Models and Data using R (Use R!), Bj\u00f8rnstad, Ottar N., Good Condition", "price": 3114, "status": "Pre-Owned", "shipping": 1130, "free_returns": false, "items_sold": null}, {"name": "Computer Networking Illuminated (Jones and Bartlett Illuminated)", "price": 1912, "status": "Pre-Owned", "shipping": 1060, "free_returns": false, "items_sold": null}, {"name": "Help Your Kids with Computer Science By DK", "price": 1378, "status": "Pre-Owned", "shipping": 0, "free_returns": false, "items_sold": null}, {"name": "Essential Computer Science: A Programmer\u2019s Guide to Foundational", "price": 3049, "status": "Pre-Owned", "shipping": 0, "free_returns": true, "items_sold": null}, {"name": "Objective-C Programming: The Big Nerd Ranch Guide Aaron Hillegass & Mikey Ward", "price": 943, "status": "Brand New", "shipping": 3230, "free_returns": false, "items_sold": null}, {"name": "Orit Hazzan Guide To Teaching Computer Science (UK IMPORT) HBOOK NEW", "price": 10992, "status": "Brand New", "shipping": 0, "free_returns": false, "items_sold": null}, {"name": "A Generative Theory of Shape (Lecture Notes in Computer Science, 2145)", "price": 5861, "status": "Pre-Owned", "shipping": 499, "free_returns": false, "items_sold": null}, {"name": "Computer Science and Statistics : Proceedings of the 13th Symposi", "price": 450, "status": "Pre-Owned", "shipping": 0, "free_returns": true, "items_sold": null}, {"name": "Leckie \u2013 PC PASSPORT BEGINNER 2ND ED: Beginner Level, Very Good Condition, SQA, ", "price": 8798, "status": "Pre-Owned", "shipping": 1038, "free_returns": false, "items_sold": null}, {"name": "Computability and Unsolvability by Davis, Prof. Martin", "price": 511, "status": "Pre-Owned", "shipping": 0, "free_returns": true, "items_sold": null}, {"name": "Coding For Dummies (For Dummies (Computers)), Abraham, Nikhil, Good Condition, I", "price": 1071, "status": "Pre-Owned", "shipping": 1123, "free_returns": false, "items_sold": null}, {"name": "GCSE OCR Computer Science: Illustrated Revi... by PG Online Paperback / softback", "price": 958, "status": "Pre-Owned", "shipping": 0, "free_returns": false, "items_sold": null}, {"name": "MATHEMATICAL STRUCTURES FOR COMPUTER SCIENCE By Judith L. Gersting - Hardcover", "price": 6395, "status": "New (Other)", "shipping": 0, "free_returns": true, "items_sold": null}, {"name": "Talking with Computers : Explorations in the Science and Technolo", "price": 450, "status": "Pre-Owned", "shipping": 0, "free_returns": false, "items_sold": null}, {"name": "Formal Specification Using Z (Computer Science ... by Lightfoot, David Paperback", "price": 608, "status": "Pre-Owned", "shipping": 0, "free_returns": false, "items_sold": null}, {"name": "Context and Consciousness: Activity Theory and Human-computer Interaction (The M", "price": 837, "status": "Pre-Owned", "shipping": 1936, "free_returns": false, "items_sold": null}, {"name": "SPSS Survival Manual, Pallant, Julie, Good Condition, ISBN 9780335261543", "price": 1520, "status": "Pre-Owned", "shipping": 1882, "free_returns": false, "items_sold": null}, {"name": "Microsoft Project 2010: The Missing Manual (Missing Manuals), Bonnie Biafore, Us", "price": 1527, "status": "Pre-Owned", "shipping": 217, "free_returns": false, "items_sold": null}, {"name": "Computer Science: A Very Short Introduction (Very Short ... by Dasgupta, Subrata", "price": 991, "status": "Pre-Owned", "shipping": 0, "free_returns": false, "items_sold": null}, {"name": "Applied modelling and computing in social science", "price": 749, "status": "New (Other)", "shipping": 0, "free_returns": false, "items_sold": null}, {"name": "ADVANCES IN COMPUTER SCIENCE - ASIAN 2006. SECURE SOFTWARE By Mitsu Okada Mint", "price": 1775, "status": "New (Other)", "shipping": 0, "free_returns": true, "items_sold": null}, {"name": "Persuasive Technology: Using Computers to Change What We Think and Do (Interacti", "price": 2870, "status": "Pre-Owned", "shipping": 1604, "free_returns": false, "items_sold": null}, {"name": "eBay Photos That Sell: Taking Great Product Shots for eBay and Beyond, Very Good", "price": 425, "status": "Pre-Owned", "shipping": 1315, "free_returns": false, "items_sold": null}, {"name": "3D Printing - Idiot's Guides Paperback Cameron Coward", "price": 546, "status": "Pre-Owned", "shipping": 0, "free_returns": false, "items_sold": null}, {"name": "Java: An Introduction to Computer Science and Pr... by Savitch, Walter Paperback", "price": 790, "status": "Pre-Owned", "shipping": 0, "free_returns": false, "items_sold": null}, {"name": "Computer Science by French, Carl Paperback Book The Fast Free Shipping", "price": 661, "status": "Pre-Owned", "shipping": 0, "free_returns": false, "items_sold": null}, {"name": "Mac Computing for Seniors in Easy Steps, Vandome, Nick, Used; Very Good Book", "price": 279, "status": "Pre-Owned", "shipping": 217, "free_returns": false, "items_sold": null}, {"name": "C. Answer Book (Prentice Hall Software S.), Tondo, Clovis L., Good Condition, IS", "price": 4283, "status": "Pre-Owned", "shipping": 801, "free_returns": false, "items_sold": null}, {"name": "FUNDAMENTALS OF DISCRETE MATH FOR COMPUTER SCIENCE: A By Tom Jenkyns & Ben VG", "price": 2275, "status": "Pre-Owned", "shipping": 0, "free_returns": true, "items_sold": null}, {"name": "Conceptual Modeling     ER 2011  30th International Conference on", "price": 12711, "status": "Brand New", "shipping": 0, "free_returns": false, "items_sold": null}, {"name": "Algorithms and Computation  21st International Symposium  ISAAC 2", "price": 12711, "status": "Brand New", "shipping": 0, "free_returns": false, "items_sold": null}, {"name": "Shop on eBay", "price": 2000, "status": "Brand New", "shipping": null, "free_returns": false, "items_sold": null}, {"name": "Algorithms and Computation  21st International Symposium  ISAAC 2", "price": 12711, "status": "Brand New", "shipping": 0, "free_returns": false, "items_sold": null}, {"name": "Optical Communications in the 5G Era by Liu (paperback)", "price": 17995, "status": "Pre-Owned", "shipping": 499, "free_returns": false, "items_sold": null}, {"name": "An ASIC Low Power Primer by Chadha (hardcover)", "price": 17995, "status": "Pre-Owned", "shipping": 499, "free_returns": false, "items_sold": null}, {"name": "Computational Collective Intelligence. Technologies And Applications: Second ...", "price": 17623, "status": "Brand New", "shipping": 0, "free_returns": false, "items_sold": null}, {"name": "Computer Science: An Overview By J. Glenn Brookshear", "price": 1099, "status": "Pre-Owned", "shipping": 0, "free_returns": false, "items_sold": null}, {"name": "Theory of Sampling and Sampling Practice\u2014third edition (author Signed/ Inscribe", "price": 19500, "status": "New (Other)", "shipping": 550, "free_returns": false, "items_sold": null}, {"name": "Computer Science Project Work : Principles and Pragmatics Hardcov", "price": 2320, "status": "Pre-Owned", "shipping": 0, "free_returns": false, "items_sold": null}, {"name": "Java for Everyone, Very Good Condition, Horstmann, Cay S., ISBN 0471791911", "price": 1457, "status": "Pre-Owned", "shipping": 2032, "free_returns": false, "items_sold": null}, {"name": "PIC: Your Personal Introductory Course, Morton, John, Used; Good Book", "price": 398, "status": "Pre-Owned", "shipping": 217, "free_returns": false, "items_sold": null}, {"name": "Build Your Own Computer: The Step-by-step Guide, MacRae, Kyle, Used; Very Good B", "price": 266, "status": "Pre-Owned", "shipping": 217, "free_returns": false, "items_sold": null}, {"name": "Microsoft Word 2002 Essentials Level 1 / 2 / & 3 Softcover Textbooks", "price": 999, "status": "New (Other)", "shipping": 416, "free_returns": false, "items_sold": null}, {"name": "Introduction to Functional Programming by Philip Wadler, Bird Prentice Hall", "price": 1177, "status": "Pre-Owned", "shipping": 2540, "free_returns": false, "items_sold": null}, {"name": "The Really, Really, Really Easy Step-by-step Computer Book (Windows 7 Edition) o", "price": 362, "status": "Pre-Owned", "shipping": 217, "free_returns": false, "items_sold": null}, {"name": "Foundations of Intelligent Systems: 18th International Symposium, ISMIS 2009 ...", "price": 21871, "status": "Brand New", "shipping": 0, "free_returns": false, "items_sold": null}, {"name": "Mathematical Morphology And Its Applications To Image And Signal Processing: ...", "price": 15051, "status": "Brand New", "shipping": 0, "free_returns": false, "items_sold": null}, {"name": "Euro-Par 2010 - Parallel Processing: 16th International Euro-Par Conference, ...", "price": 17623, "status": "Brand New", "shipping": 0, "free_returns": false, "items_sold": null}, {"name": "ENCYCLOPEDIA OF COMPUTER SCIENCE AND TECHNOLOGY: VOLUME 13 By Jack Belzer VG", "price": 14995, "status": "Pre-Owned", "shipping": 0, "free_returns": true, "items_sold": null}, {"name": "Unix for Super-Users (International computer science series)", "price": 499, "status": "Pre-Owned", "shipping": 0, "free_returns": false, "items_sold": null}, {"name": "Don't Make Me Think!: A Common Sense Approach to Web Usability, Steve Krug, Good", "price": 462, "status": "Pre-Owned", "shipping": 963, "free_returns": false, "items_sold": null}, {"name": "Natural Language Understanding by Allen, James", "price": 409, "status": "Pre-Owned", "shipping": 0, "free_returns": true, "items_sold": null}, {"name": "PROBABILITY MODELS FOR COMPUTER SCIENCE By Sheldon M. Ross **BRAND NEW**", "price": 4775, "status": "Brand New", "shipping": 0, "free_returns": true, "items_sold": null}, {"name": "Core Java for the Impatient - Cay Horstmann Book Textbook Pearson", "price": 2238, "status": "Pre-Owned", "shipping": 2211, "free_returns": false, "items_sold": null}, {"name": "HAL's Legacy: \"2001's\" Computer as Dream and Reality,David Stork", "price": 582, "status": "Pre-Owned", "shipping": 1060, "free_returns": false, "items_sold": null}, {"name": "CGP Books : GCSE Computer Science AQA Revision Guide FREE Shipping, Save \u00a3s", "price": 486, "status": "Pre-Owned", "shipping": 470, "free_returns": false, "items_sold": 27}, {"name": "UNDERSTANDING COMPUTER SCIENCE (UNDERSTANDING SERIES) By Roger S Walker *VG+*", "price": 3695, "status": "Pre-Owned", "shipping": 0, "free_returns": true, "items_sold": null}, {"name": "Invitation to Computer Science Paperback Kenneth Lambert", "price": 546, "status": "Pre-Owned", "shipping": 0, "free_returns": false, "items_sold": null}, {"name": "(Good)-From Logic to Computers (Computer Science Texts) (paperback)--0632011831", "price": 404, "status": "Pre-Owned", "shipping": 530, "free_returns": false, "items_sold": null}, {"name": "IT for Parents: How to Help Your Child (How to help your child series), , Good C", "price": 334, "status": "Pre-Owned", "shipping": 278, "free_returns": false, "items_sold": null}, {"name": "On The Move To Meaningful Internet Systems: Confederated International Confer...", "price": 15051, "status": "Brand New", "shipping": 0, "free_returns": false, "items_sold": null}, {"name": "Programming Languages And Systems: 8th Asian Symposium, Aplas 2010, Shanghai,...", "price": 15051, "status": "Brand New", "shipping": 0, "free_returns": false, "items_sold": null}, {"name": "Programs, Proofs, Processes: 6th Conference On Computability In Europe, Cie, ...", "price": 17623, "status": "Brand New", "shipping": 0, "free_returns": false, "items_sold": null}, {"name": "Pattern Recognition and Image Analysis: 9th Iberian Conference, Ibpria 2019, ...", "price": 15314, "status": "Brand New", "shipping": 0, "free_returns": false, "items_sold": null}, {"name": "Encyclopedia of Computer Science & Engineering  hardcover Used - Good", "price": 1020, "status": "Pre-Owned", "shipping": 399, "free_returns": true, "items_sold": null}, {"name": "Algorithmic Aspects of Wireless Sensor Networks: Fourth International Workshop, ", "price": 1603, "status": "Brand New", "shipping": 0, "free_returns": false, "items_sold": null}, {"name": "The Complete Idiots Guide to Microsoft Windows 98, McFedries, Paul, Used; Good B", "price": 367, "status": "Pre-Owned", "shipping": 217, "free_returns": false, "items_sold": null}, {"name": "Office 2003 for Dummies, Wang, Wallace, Used; Good Book", "price": 263, "status": "Pre-Owned", "shipping": 217, "free_returns": false, "items_sold": null}, {"name": "iPhone 5 Portable Genius, McFedries, Paul, Used; Good Book", "price": 262, "status": "Pre-Owned", "shipping": 217, "free_returns": false, "items_sold": null}, {"name": "How to Do Everything with PHP and MySQL, Vaswani, Vikram, Used; Good Book", "price": 305, "status": "Pre-Owned", "shipping": 217, "free_returns": false, "items_sold": null}, {"name": "Foundations of Intelligent Systems : 19th International Symposium, ISMIS 2011...", "price": 19171, "status": "Brand New", "shipping": 0, "free_returns": false, "items_sold": null}, {"name": "Advances in Conceptual Modeling     Applications and Challenges  ", "price": 11581, "status": "Brand New", "shipping": 0, "free_returns": false, "items_sold": null}, {"name": "Resisting the Virtual Life: Culture and Politics of Information, , Used; Good Bo", "price": 361, "status": "Pre-Owned", "shipping": 217, "free_returns": false, "items_sold": null}, {"name": "How to Do Everything with Your iMac, 4th Edition, Stauffer, Todd, Used; Good Boo", "price": 358, "status": "Pre-Owned", "shipping": 217, "free_returns": false, "items_sold": null}, {"name": "WebPlus X8 Resource Guide, Serif Europe Limited, Used; Good Book", "price": 362, "status": "Pre-Owned", "shipping": 217, "free_returns": false, "items_sold": null}, {"name": "Website Design Made Easy, Williams, Richard N., Used; Very Good Book", "price": 361, "status": "Pre-Owned", "shipping": 217, "free_returns": false, "items_sold": null}, {"name": "eBay\ufffd QuickSteps, Second Edition, Matthews, Carole & Cronan, John, Used; Good Bo", "price": 242, "status": "Pre-Owned", "shipping": 217, "free_returns": false, "items_sold": null}, {"name": "Brilliant Office 2007, Johnson, Mr Steve, Used; Good Book", "price": 367, "status": "Pre-Owned", "shipping": 217, "free_returns": false, "items_sold": null}, {"name": "J2ME in a Nutshell (In a Nutshell (OReilly)), Kim Topley, Used; Good Book", "price": 367, "status": "Pre-Owned", "shipping": 217, "free_returns": false, "items_sold": null}, {"name": "JAVA 9 MODULARITY - SANDER MAK & PAUL BAKKER - O\u2019REILLY BOOK TEXTBOOKS", "price": 1767, "status": "Pre-Owned", "shipping": 2200, "free_returns": false, "items_sold": null}, {"name": "Elements of Finite Model Theory (Texts in Theoretical Computer S", "price": 7576, "status": "Pre-Owned", "shipping": 1060, "free_returns": false, "items_sold": null}, {"name": "Java and Eclipse for Computer Sc... 099118873X by Liming, Sean D., Malin, John R", "price": 3598, "status": "Pre-Owned", "shipping": 399, "free_returns": false, "items_sold": null}, {"name": "Home Networking with Microsoft\ufffd Windows\ufffd XP Step by Step (Step by Step (Microsof", "price": 222, "status": "Pre-Owned", "shipping": 217, "free_returns": false, "items_sold": null}, {"name": "Mathematical Modelling Techniques Paperback Rutherford Aris", "price": 623, "status": "Pre-Owned", "shipping": 0, "free_returns": false, "items_sold": null}, {"name": "Algorithms to Live By: The Computer Science of Human Decisions", "price": 1740, "status": "Brand New", "shipping": 0, "free_returns": false, "items_sold": null}, {"name": "Excel Sales Forecast For Dummies, Carlberg, Conrad, Good Condition, ISBN 0764575", "price": 1266, "status": "Pre-Owned", "shipping": 2042, "free_returns": false, "items_sold": null}, {"name": "Computer Science and Statistics : Proceedings of the 14th Symposi", "price": 450, "status": "Pre-Owned", "shipping": 0, "free_returns": false, "items_sold": null}, {"name": "Computer Vision \ufffd ACCV 2018: 14th Asian Conference on Computer Vision, Perth, Au", "price": 3999, "status": "Brand New", "shipping": 0, "free_returns": false, "items_sold": null}, {"name": "Scanning & Editing Your Old Photos in Simple Steps, Morris, Ms Heather, Good Con", "price": 331, "status": "Pre-Owned", "shipping": 1016, "free_returns": false, "items_sold": null}, {"name": "Word Processing with Word for Windows (Prisma computer guides), Koelma, Anita, U", "price": 499, "status": "Pre-Owned", "shipping": 217, "free_returns": false, "items_sold": null}, {"name": "ICDL 4: The Complete Coursebook, Holden, Mr Paul, Used; Good Book", "price": 442, "status": "Pre-Owned", "shipping": 217, "free_returns": false, "items_sold": null}, {"name": "JAVA: LAB MANUAL: AN INTRODUCTION TO COMPUTER SCIENCE AND By Walter Savitch NEW", "price": 3895, "status": "Brand New", "shipping": 0, "free_returns": true, "items_sold": null}, {"name": "Physics for Computer Science Students", "price": 4256, "status": "Pre-Owned", "shipping": 0, "free_returns": true, "items_sold": null}, {"name": "Starting Out With Visual C#, 4th Edition, Tony Gaddis", "price": 1500, "status": "Pre-Owned", "shipping": 0, "free_returns": false, "items_sold": null}, {"name": "1985 \u2018132 Short Programs For The Mathematics Classroom\u2019 By John Higgo", "price": 1177, "status": "Pre-Owned", "shipping": 2671, "free_returns": false, "items_sold": null}, {"name": "Mathematics and Computation : A Theory Revolutionizing Technology and Science by", "price": 3500, "status": "New (Other)", "shipping": 483, "free_returns": false, "items_sold": null}, {"name": "Programming Ada 2012 John Barnes Paperback Cambridge University P\u2026 9781107424814", "price": 1448, "status": "New (Other)", "shipping": 3181, "free_returns": false, "items_sold": null}, {"name": "Web Technologies : A Computer Science Perspective by Jeffrey C. Jackson (Perf...", "price": 744, "status": "Pre-Owned", "shipping": 399, "free_returns": false, "items_sold": null}, {"name": "Policy", "price": 1423, "status": "Pre-Owned", "shipping": 0, "free_returns": false, "items_sold": null}, {"name": "CCNA 200-301 Official Cert Guide, Volume 1/e, Very Good Condition, Odom, Wendell", "price": 2339, "status": "Pre-Owned", "shipping": 3796, "free_returns": false, "items_sold": null}, {"name": "A Book Apart Books: Responsive Web Design & Mobile First", "price": 707, "status": "New (Other)", "shipping": 3226, "free_returns": false, "items_sold": null}, {"name": "Advances in Multimedia Information Systems: 4th Internat... Paperback / softback", "price": 5951, "status": "Pre-Owned", "shipping": 0, "free_returns": false, "items_sold": null}, {"name": "Digital Multimedia by Chapman, Nigel; Chapman, Jenny", "price": 695, "status": "Pre-Owned", "shipping": 0, "free_returns": true, "items_sold": null}, {"name": "Algorithms to Live By: The Computer Science of Human Decisions", "price": 1740, "status": "Brand New", "shipping": 0, "free_returns": false, "items_sold": null}, {"name": "Learning Java, Patrick Niemeyer & Jonathan Knudsen, Used; Good Book", "price": 494, "status": "Pre-Owned", "shipping": 217, "free_returns": false, "items_sold": null}, {"name": "Objects  Components  Models  Patterns  49th International Confere", "price": 11581, "status": "Brand New", "shipping": 0, "free_returns": false, "items_sold": null}, {"name": "Spatial Information Theory  10th International Conference  COSIT ", "price": 11581, "status": "Brand New", "shipping": 0, "free_returns": false, "items_sold": null}]